{
    "bilder": [
        "DJI_0289.JPG",
        "DJI_0288.JPG",
        "DJI_0287.JPG",
        "DJI_0286.JPG",
        "DJI_0285.JPG",
        "DJI_0284.JPG"
    ],
    "passpunkte": [
        {
            "passpunkt": 0,
            "image": 0,
            "x": 830.7972047639337,
            "y": 2635.0598909840774
        },
        {
            "passpunkt": 1,
            "image": 0,
            "x": 3284.3768088487323,
            "y": 2735.6643645698327
        },
        {
            "passpunkt": 2,
            "image": 0,
            "x": 1539.641028838163,
            "y": 1280.311605934375
        },
        {
            "passpunkt": 2,
            "image": 0,
            "x": 1539.641028838163,
            "y": 1280.311605934375
        },
        {
            "passpunkt": 2,
            "image": 1,
            "x": 1246.5859335937505,
            "y": 1493.6522382812493
        },
        {
            "passpunkt": 2,
            "image": 2,
            "x": 1327.4478284457414,
            "y": 2041.1498942448495
        },
        {
            "passpunkt": 2,
            "image": 3,
            "x": 1333.4960937500005,
            "y": 1586.9140625000007
        },
        {
            "passpunkt": 2,
            "image": 4,
            "x": 2371.815061487119,
            "y": 1516.4171042213152
        },
        {
            "passpunkt": 0,
            "image": 5,
            "x": 1237.3046875000005,
            "y": 2186.5234375000005
        },
        {
            "passpunkt": 0,
            "image": 4,
            "x": 2033.203125000001,
            "y": 2284.179687500001
        },
        {
            "passpunkt": 0,
            "image": 3,
            "x": 633.7890625000005,
            "y": 2304.687500000001
        },
        {
            "passpunkt": 0,
            "image": 2,
            "x": 571.8677818953719,
            "y": 2993.1242914437144
        },
        {
            "passpunkt": 0,
            "image": 1,
            "x": 872.703851701128,
            "y": 2417.2588006475785
        },
        {
            "passpunkt": 1,
            "image": 1,
            "x": 2338.3789062500005,
            "y": 2424.8046875000005
        },
        {
            "passpunkt": 1,
            "image": 3,
            "x": 1892.0414224135973,
            "y": 2276.771522389125
        },
        {
            "passpunkt": 1,
            "image": 4,
            "x": 3730.957031250002,
            "y": 2249.023437500002
        },
        {
            "passpunkt": 1,
            "image": 4,
            "x": 3730.6556229638286,
            "y": 2249.246091148734
        },
        {
            "passpunkt": 1,
            "image": 5,
            "x": 2889.916547594469,
            "y": 2315.697797594468
        },
        {
            "passpunkt": 3,
            "image": 0,
            "x": 3130.1404771103466,
            "y": 146.4832843534852
        },
        {
            "passpunkt": 3,
            "image": 1,
            "x": 2325.7783447903103,
            "y": 937.7117574165296
        },
        {
            "passpunkt": 3,
            "image": 2,
            "x": 1971.19140625,
            "y": 1305.6640625
        },
        {
            "passpunkt": 3,
            "image": 3,
            "x": 1935.686951811378,
            "y": 760.1873952898136
        },
        {
            "passpunkt": 3,
            "image": 4,
            "x": 3436.5234375000005,
            "y": 609.8632812499993
        },
        {
            "passpunkt": 3,
            "image": 5,
            "x": 2765.3808593749986,
            "y": 788.5742187499999
        },
        {
            "passpunkt": 4,
            "image": 5,
            "x": 1774.9023437500002,
            "y": 1720.7031250000005
        },
        {
            "passpunkt": 4,
            "image": 1,
            "x": 2156.723607548969,
            "y": 1514.0350182813722
        },
        {
            "passpunkt": 4,
            "image": 0,
            "x": 2810.058593750001,
            "y": 1377.44140625
        },
        {
            "passpunkt": 4,
            "image": 5,
            "x": 1774.9085490134592,
            "y": 1720.3771478815536
        },
        {
            "passpunkt": 5,
            "image": 3,
            "x": 1465.8652520147389,
            "y": 1962.8652145882766
        },
        {
            "passpunkt": 5,
            "image": 0,
            "x": 1160.6445312500005,
            "y": 1562.5
        },
        {
            "passpunkt": 6,
            "image": 4,
            "x": 2548.0618976813676,
            "y": 1853.465366870104
        },
        {
            "passpunkt": 6,
            "image": 0,
            "x": 1837.8906250000005,
            "y": 1493.1640625000007
        },
        {
            "passpunkt": 7,
            "image": 0,
            "x": 1209.9609375000005,
            "y": 2024.4140624999995
        },
        {
            "passpunkt": 7,
            "image": 2,
            "x": 1730.7516826415213,
            "y": 2637.1096059405118
        },
        {
            "passpunkt": 8,
            "image": 0,
            "x": 248.8781506516995,
            "y": 2098.1132330813507
        },
        {
            "passpunkt": 8,
            "image": 1,
            "x": 450.1953125000009,
            "y": 2080.5664062499995
        },
        {
            "passpunkt": 8,
            "image": 2,
            "x": 317.16133356478144,
            "y": 2635.161599533732
        },
        {
            "passpunkt": 8,
            "image": 3,
            "x": 392.08984375000085,
            "y": 2027.34375
        },
        {
            "passpunkt": 8,
            "image": 4,
            "x": 1645.5078125000007,
            "y": 1977.5390625
        },
        {
            "passpunkt": 8,
            "image": 5,
            "x": 648.2993590668661,
            "y": 1662.6547895570257
        },
        {
            "passpunkt": 9,
            "image": 5,
            "x": 2764.7585700771288,
            "y": 1584.9645863156536
        },
        {
            "passpunkt": 9,
            "image": 4,
            "x": 3567.6513687178017,
            "y": 1464.2541281284534
        },
        {
            "passpunkt": 9,
            "image": 1,
            "x": 2313.6720172052233,
            "y": 1731.9513623595665
        },
        {
            "passpunkt": 9,
            "image": 0,
            "x": 3167.9687500000005,
            "y": 1501.953125
        },
        {
            "passpunkt": 10,
            "image": 1,
            "x": 1993.3571984460639,
            "y": 1771.6347309332123
        },
        {
            "passpunkt": 10,
            "image": 0,
            "x": 2748.349049247567,
            "y": 1763.3229372479318
        },
        {
            "passpunkt": 10,
            "image": 1,
            "x": 1993.105265921886,
            "y": 1771.0835265474957
        }
    ]
}